sais/__init__.py
sais/notify/__init__.py
sais/notify/auth/__init__.py
sais/notify/auth/auth_info.py
sais/notify/clients/__init__.py
sais/notify/clients/notify_client.py
sais/notify/config/__init__.py
sais/notify/config/const.py
sais/notify/config/version.py
sais/notify/handler/__init__.py
sais/notify/handler/keepalive_handler.py
sais/notify/handler/message_handler.py
sais/notify/model/__init__.py
sais/notify/model/keepalive_model.py
sais/notify/model/message_model.py
sais/notify/types/__init__.py
sais_notify-0.0.15.dist-info/METADATA
sais_notify-0.0.15.dist-info/WHEEL
sais_notify-0.0.15.dist-info/RECORD
