Metadata-Version: 2.3
Name: sais-notify
Version: 0.0.15
Summary: sais notify python sdk
Project-URL: repository, https://github.com/xxx/xxxx
Author: SAIS Contributors
Author-email: sais@example.com
License: Apache License 2.0
Keywords: sais,sais-notify
Classifier: Programming Language :: Python :: 3.8
Classifier: Topic :: Software Development :: Libraries
Classifier: Topic :: Software Development :: Libraries :: Python Modules
Requires-Python: >=3.8
Requires-Dist: pydantic~=2.4.2
Requires-Dist: requests~=2.28.2
Requires-Dist: setuptools~=60.2.0
Requires-Dist: tqdm~=4.65.0
Provides-Extra: test
